odoo/addons/sale_stock_available_to_promise_release_dropshipping/README.rst
odoo/addons/sale_stock_available_to_promise_release_dropshipping/__init__.py
odoo/addons/sale_stock_available_to_promise_release_dropshipping/__manifest__.py
odoo/addons/sale_stock_available_to_promise_release_dropshipping/i18n/it.po
odoo/addons/sale_stock_available_to_promise_release_dropshipping/i18n/sale_stock_available_to_promise_release_dropshipping.pot
odoo/addons/sale_stock_available_to_promise_release_dropshipping/models/__init__.py
odoo/addons/sale_stock_available_to_promise_release_dropshipping/models/sale_order_line.py
odoo/addons/sale_stock_available_to_promise_release_dropshipping/readme/CONTRIBUTORS.rst
odoo/addons/sale_stock_available_to_promise_release_dropshipping/readme/DESCRIPTION.rst
odoo/addons/sale_stock_available_to_promise_release_dropshipping/static/description/icon.png
odoo/addons/sale_stock_available_to_promise_release_dropshipping/static/description/index.html
odoo13_addon_sale_stock_available_to_promise_release_dropshipping-13.0.1.0.1.dev5.dist-info/METADATA
odoo13_addon_sale_stock_available_to_promise_release_dropshipping-13.0.1.0.1.dev5.dist-info/WHEEL
odoo13_addon_sale_stock_available_to_promise_release_dropshipping-13.0.1.0.1.dev5.dist-info/top_level.txt
odoo13_addon_sale_stock_available_to_promise_release_dropshipping-13.0.1.0.1.dev5.dist-info/RECORD
